givemeconformer/__init__.py
givemeconformer/__main__.py
givemeconformer/api.py
givemeconformer/cli.py
givemeconformer/version.py
givemeconformer-0.0.1.dist-info/LICENSE
givemeconformer-0.0.1.dist-info/METADATA
givemeconformer-0.0.1.dist-info/WHEEL
givemeconformer-0.0.1.dist-info/entry_points.txt
givemeconformer-0.0.1.dist-info/top_level.txt
givemeconformer-0.0.1.dist-info/RECORD
